pypeline/__init__.py
pypeline/markup.py
pypeline/markups.py
pypeline/tests/__init__.py
pypeline/tests/test_markup.py
pypeline/tests/test_readme.py
Pypeline-0.7.0.dist-info/METADATA
Pypeline-0.7.0.dist-info/WHEEL
Pypeline-0.7.0.dist-info/top_level.txt
Pypeline-0.7.0.dist-info/zip-safe
Pypeline-0.7.0.dist-info/RECORD
